LICENSE
Makefile
README.md
VERSION
__main__.py
ez_setup.py
requirements.txt
setup.py
bin/lightbulb
docker/Dockerfile
docker/entrypoint.sh
examples/test_difflearn_browser_browser.txt
examples/test_difflearn_browser_waf_modsec.txt
examples/test_difflearn_browser_waf_phpids.txt
examples/test_difflearn_mysql_waf.txt
examples/test_difflearn_mysql_waf_phpids.txt
examples/test_difflearn_waf_waf.txt
examples/test_distinguish_waf.txt
examples/test_gen_tree.txt
examples/test_learn_browser.txt
examples/test_learn_browser_filter.txt
examples/test_learn_mysql.txt
examples/test_learn_waf.txt
examples/test_learn_waf_grammar.txt
examples/test_verify.txt
libs/MySQLdb.py
libs/__init__.py
libs/_multiprocessing.py
libs/_weakrefset.py
libs/ctypes.py
libs/handlers.py
libs/models.py
libs/pkg_resources.py
libs/threading.py
lightbulb/__init__.py
lightbulb/lightbulb.py
lightbulb/api/__init__.py
lightbulb/api/api.py
lightbulb/api/api_native.py
lightbulb/api/gentree.py
lightbulb/cli/__init__.py
lightbulb/cli/show.py
lightbulb/cli/use.py
lightbulb/core/__init__.py
lightbulb/core/base.py
lightbulb/core/operate.py
lightbulb/core/modules/__init__.py
lightbulb/core/modules/gofa.py
lightbulb/core/modules/sfadiff.py
lightbulb/core/utils/SimpleWebServer.py
lightbulb/core/utils/SimpleWebSocketServer.py
lightbulb/core/utils/__init__.py
lightbulb/core/utils/browserfilterhandler.py
lightbulb/core/utils/browserhandler.py
lightbulb/core/utils/common.py
lightbulb/core/utils/httphandler.py
lightbulb/core/utils/ipc.py
lightbulb/core/utils/rawhttphandler.py
lightbulb/core/utils/rcadiff.py
lightbulb/core/utils/sockethandler.py
lightbulb/core/utils/sqlhandler.py
lightbulb/core/utils/webserverhandler.py
lightbulb/core/utils/webserveriframehandler.py
lightbulb/data/__init__.py
lightbulb/data/configs.py
lightbulb/data/grammars.py
lightbulb/data/regex.py
lightbulb/data/trees.py
lightbulb/data/configs/waf_conf1.json
lightbulb/data/configs/waf_conf1.py
lightbulb/data/grammars/attribute_swf_xss.py
lightbulb_framework.egg-info/PKG-INFO
lightbulb_framework.egg-info/SOURCES.txt
lightbulb_framework.egg-info/dependency_links.txt
lightbulb_framework.egg-info/entry_points.txt
lightbulb_framework.egg-info/namespace_packages.txt
lightbulb_framework.egg-info/not-zip-safe
lightbulb_framework.egg-info/requires.txt
lightbulb_framework.egg-info/top_level.txt
