Metadata-Version: 1.1
Name: lightbulb-framework
Version: 0.0.18
Summary: Tools for auditing WAFS
Home-page: https://github.com/lightbulb-framework/lightbulb-framework
Author: George Argyros, Ioannis Stais
Author-email: ioannis.stais@gmail.com
License: UNKNOWN
Download-URL: https://github.com/lightbulb-framework/lightbulb-framework/tarball/master
Platform: Any
Classifier: Development Status :: 3 - Alpha
Classifier: Programming Language :: Python
Classifier: Programming Language :: Python :: 2
Classifier: Programming Language :: Python :: 2.7
Classifier: Environment :: Console
